Metadata-Version: 1.1
Name: pytransformation
Version: 0.1
Summary: Source code transformations for cross-compilation.
Home-page: https://github.com/Dyfox100/pytransformation
Author: Dylan Fox
Author-email: dylan.fox@colorado.edu
License: GPLv3
Download-URL: https://github.com/Dyfox100/pytransformation/archive/v0.1.tar.gz
Platform: UNKNOWN
Classifier: Development Status :: 3 - Alpha
Classifier: Intended Audience :: Developers
Classifier: Topic :: Software Development :: Build Tools
Classifier: Programming Language :: Python :: 3.7
Classifier: Programming Language :: Python :: 3.8
Classifier: Programming Language :: Python :: 3.9
